odoo/addons/sale_procurement_amendment/README.rst
odoo/addons/sale_procurement_amendment/__init__.py
odoo/addons/sale_procurement_amendment/__manifest__.py
odoo/addons/sale_procurement_amendment/i18n/ca.po
odoo/addons/sale_procurement_amendment/i18n/es.po
odoo/addons/sale_procurement_amendment/i18n/it.po
odoo/addons/sale_procurement_amendment/i18n/sale_procurement_amendment.pot
odoo/addons/sale_procurement_amendment/models/__init__.py
odoo/addons/sale_procurement_amendment/models/sale_order_line.py
odoo/addons/sale_procurement_amendment/models/stock_move.py
odoo/addons/sale_procurement_amendment/models/stock_picking.py
odoo/addons/sale_procurement_amendment/readme/CONTRIBUTORS.rst
odoo/addons/sale_procurement_amendment/readme/DESCRIPTION.rst
odoo/addons/sale_procurement_amendment/readme/HISTORY.rst
odoo/addons/sale_procurement_amendment/readme/INSTALL.rst
odoo/addons/sale_procurement_amendment/readme/USAGE.rst
odoo/addons/sale_procurement_amendment/static/description/icon.png
odoo/addons/sale_procurement_amendment/static/description/index.html
odoo/addons/sale_procurement_amendment/tests/__init__.py
odoo/addons/sale_procurement_amendment/tests/test_sale_procurement_amendment.py
odoo14_addon_sale_procurement_amendment-14.0.1.0.1.dev12.dist-info/METADATA
odoo14_addon_sale_procurement_amendment-14.0.1.0.1.dev12.dist-info/WHEEL
odoo14_addon_sale_procurement_amendment-14.0.1.0.1.dev12.dist-info/top_level.txt
odoo14_addon_sale_procurement_amendment-14.0.1.0.1.dev12.dist-info/RECORD
