Metadata-Version: 2.1
Name: odoo14-addon-sale_procurement_amendment
Version: 14.0.1.0.1.dev12
Summary: Allow to reflect confirmed sale lines quantity amendments to procurements
Home-page: https://github.com/OCA/sale-workflow
Author: ACSONE SA/NV,Odoo Community Association (OCA)
Author-email: support@odoo-community.org
License: AGPL-3
Classifier: Programming Language :: Python
Classifier: Framework :: Odoo
Classifier: Framework :: Odoo :: 14.0
Classifier: License :: OSI Approved :: GNU Affero General Public License v3
Classifier: Development Status :: 5 - Production/Stable
Requires-Python: >=3.6
Requires-Dist: odoo14-addon-sale-order-line-chained-move
Requires-Dist: odoo<14.1dev,>=14.0a
